proword/__init__.py
proword-0.1.1.dist-info/LICENSE
proword-0.1.1.dist-info/METADATA
proword-0.1.1.dist-info/WHEEL
proword-0.1.1.dist-info/RECORD
