Metadata-Version: 2.1
Name: proword
Version: 0.1.1
Summary: proword is a python package allowing you to develop terminal applications while being modular and flexible. 
Home-page: https://github.com/JAGDC/Proword
License: MIT
Author: Adam Garza
Author-email: 117498948+TVRework@users.noreply.github.com
Requires-Python: >=3.8,<4.0
Classifier: License :: OSI Approved :: MIT License
Classifier: Programming Language :: Python :: 3
Classifier: Programming Language :: Python :: 3.8
Classifier: Programming Language :: Python :: 3.9
Classifier: Programming Language :: Python :: 3.10
Classifier: Programming Language :: Python :: 3.11
Requires-Dist: attrs (>=23.1.0,<24.0.0)
Requires-Dist: nox-poetry (>=1.0.3,<2.0.0)
Requires-Dist: requests (>=2.31.0,<3.0.0)
Project-URL: Repository, https://github.com/JAGDC/Proword
